llmeval-0.4.1.dist-info/METADATA
llmeval-0.4.1.dist-info/WHEEL
llmeval-0.4.1.dist-info/entry_points.txt
llmeval/__version__.py
llmeval/eval.py
llmeval/examples/llmeval.yaml
llmeval/examples/prompts/capitals.yaml
llmeval/examples/prompts/code.yaml
llmeval/examples/prompts/code_metrics_rollup.yaml
llmeval/examples/prompts/grading.yaml
llmeval/examples/prompts/math.yaml
llmeval/examples/prompts/noop.yaml
llmeval/examples/prompts/ping.yaml
llmeval/examples/prompts/summary.yaml
llmeval/examples/prompts/tests/capitals.yaml
llmeval/examples/prompts/tests/code.yaml
llmeval/examples/prompts/tests/code_metrics_rollup.yaml
llmeval/examples/prompts/tests/grading.yaml
llmeval/examples/prompts/tests/math.yaml
llmeval/examples/prompts/tests/noop.yaml
llmeval/examples/prompts/tests/ping.yaml
llmeval/examples/prompts/tests/summary.yaml
llmeval/main.py
llmeval/utils.py
llmeval-0.4.1.dist-info/RECORD
