Metadata-Version: 2.1
Name: llmeval
Version: 0.4.1
Author-Email: Log10 team <team@log10.io>
Project-URL: Homepage, https://log10.io/docs/evaluation/installation
Requires-Python: >=3.10
Requires-Dist: click>=8.1.6
Requires-Dist: hydra-core>=1.3.2
Requires-Dist: semver>=3.0.1
Requires-Dist: log10-io>=0.4.0
